Workbook

Sheet Cover
B2: NEXFORGE MANUFACTURING LTD.
B5: Financial Modeling Test — Intern Assessment
B7: Company | C7: NexForge Manufacturing Ltd. (Fictional)
B8: Sector | C8: Industrial Manufacturing — Metal Components
B9: Test Type | C9: 3-Statement Model + DCF Valuation
B10: Level | C10: Intermediate
B11: Currency | C11: USD ($ Millions unless stated)
B13: Instructions
B14: 1. Complete all yellow-highlighted cells in the Income Statement, Balance Sheet, Cash Flow, and DCF sheets.
B15: 2. Blue cells are hardcoded inputs — do NOT change them.
B16: 3. All projection formulas must reference assumption cells — no hardcoding of calculated values.
B17: 4. Ensure the Balance Sheet balances (Assets = Liabilities + Equity) for all years.
B18: 5. Build a DCF using the projected Free Cash Flows with the given WACC and terminal growth rate.
B19: 6. Format all numbers to two decimal places where applicable; use parentheses for negatives.
B20: 7. All sheets must be linked — changes in assumptions must flow through automatically.
B21: 8. Summarize the financial model clearly in summary tab, highlighting key assumptions, drivers, and structure in a concise manner.
B22: 9. Provide financial analysis and a final investment recommendation based on the model’s outputs and underlying assumptions.
B23: 10. Ensure the work is original with no AI-generated or plagiarized content.
B25: Candidate Name: Aritra Tarafdar Date: 29-04-2026

Sheet Summary
B1: Summarise your Financial Model here
B2: Company Overview: NexForge Manufacturing - Financial Model Summary
B3: Key Valuation Outputs Implied Share Price: $14.74 Equity Value: $1,474 million Enterprise Value: $1,433 million Shares Outstanding: 100 million
B8: Model Structure This DCF model projects NexForge's financials from 2022-2027 using: Income Statement (revenue through net income) Balance Sheet (assets, liabilities, equity) Cash Flow Statement (operating, investing, financing) DCF Valuation (discounted free cash flows + terminal value)
B14: Key Assumptions Growth & Revenue Drivers: 1. Revenue Growth Rate: 10.0% annually (2023-2027) 2. 2027 Revenue: $773mm (from $480mm in 2022) Profitability Assumptions: 1. COGS: 60.0% of revenue (stable) 2. SG&A: Declining from 15.0% to 13.4% (operating leverage) 3. Tax Rate: 25.0% Capital Structure: 1. D&A: $28mm (2022) → $40.88mm (2027) 2. Interest Expense: $8mm (2022) → $4.67mm (2027) - declining with debt paydown 3. CapEx: $38mm (2022) → $50.88mm (2027) - supporting growth 4. Debt Repayment: $10mm annually DCF Valuation Inputs: 1. WACC: 10.0% 2. Terminal Growth Rate: 3.5% 3. Net Debt (FY2024): ($41mm) - net cash position Key Performance Metrics (2022 → 2027) 1. Revenue: $480mm → $773mm (61% growth) 2. EBITDA: $120mm → $206mm (72% growth) 3. EBITDA Margin: 25.0% → 26.6% (margin expansion) 4. Net Income: $63mm → $120mm (90% growth) 5. Net Margin: 13.1% → 15.53% (profitability improvement) 6. Free Cash Flow: ~$53mm → ~$98mm (strong cash generation)
B41: FINANCIAL ANALYSIS & INVESTMENT RECOMMENDATION Financial Health & Valuation Summary NexForge demonstrates strong financial fundamentals with EBITDA margins expanding from 25.0% to 26.6% driven by operating leverage as SG&A declines from 15.0% to 13.4% of revenue, while net margins improve from 13.1% to 15.53% benefiting from both operational efficiency and declining interest expense. The balance sheet strengthens dramatically with net debt improving from $75mm to net cash of $298mm by 2027, while operating cash flow grows 64% to $149mm and free cash flow nearly doubles to $98mm, demonstrating exceptional cash generation capability and self-funded growth without external financing dependency. The DCF yields an implied price of $14.74 with valuation multiples of approximately 6.9x EV/EBITDA and 12.3x P/E, which appear reasonable and potentially conservative for a quality manufacturer showing margin expansion and fortress balance sheet characteristics. Investment Recommendation: HOLD / CONDITIONAL BUY The model supports a HOLD rating with potential upgrade to BUY upon further validation, as NexForge offers attractive fundamentals including strong cash generation, credible margin expansion, balance sheet transformation, and reasonable valuation multiples, but significant risks warrant caution including high terminal value dependence (70% of enterprise value), absence of cyclical scenario analysis despite manufacturing's inherent cyclicality, constant 10% WACC assumption that likely overstates discount rates in later years given improving balance sheet, and limited visibility on customer concentration, competitive positioning, and management quality that are critical to achieving projected growth. A BUY rating would require evidence of management's execution track record, customer contract visibility supporting revenue assumptions, downside scenario testing showing limited risk at $14.74, and industry tailwinds validating the margin expansion thesis, while a SELL would be triggered by margin pressure, customer losses, CapEx exceeding projections, or recession scenarios revealing material cash flow impairment. Recommended action items include building bull/base/bear scenario analysis with probability weighting, developing sensitivity tables for key assumption combinations, conducting comparable company and precedent transaction analysis, assessing management quality and track record, performing detailed industry and competitive analysis, and stress-testing downside scenarios to understand risk profile before establishing position.

Sheet Assumptions
B1: NEXFORGE MANUFACTURING — KEY ASSUMPTIONS
C3: 2022 | D3: 2023 | E3: 2024 | F3: 2025 | G3: 2026 | H3: 2027
B4: ← Historical → | F4: ← Projections →
B5: Income Statement Assumptions
B6: Revenue Growth Rate | C6: N/A | D6: 0.1 | E6: 0.1 | F6: =AVERAGE(D6:E6) -> 0.1 | G6: =AVERAGE(E6:F6) -> 0.1 | H6: =AVERAGE(F6:G6) -> 0.1
B7: COGS % of Revenue | C7: 0.6 | D7: 0.6 | E7: 0.6 | F7: =AVERAGE(D7:E7) -> 0.6 | G7: =AVERAGE(E7:F7) -> 0.6 | H7: =AVERAGE(F7:G7) -> 0.6
B8: SG&A % of Revenue | C8: 0.15 | D8: 0.15 | E8: 0.14 | F8: =E8 - 0.2% -> 0.138 | G8: =F8 - 0.2% -> 0.136 | H8: =G8 - 0.2% -> 0.134
B9: D&A ($ mm) | C9: 28 | D9: 30 | E9: 33 | F9: =E9+(((D9-C9)+(E9-D9))/2) -> 35.5 | G9: =F9+(((E9-D9)+(F9-E9))/2) -> 38.25 | H9: =G9+(((F9-E9)+(G9-F9))/2) -> 40.875
B10: Interest Expense ($ mm) | C10: 8 | D10: 8 | E10: 7 | F10: 6.05 | G10: 5.33 | H10: 4.67
B11: Tax Rate | C11: 0.25 | D11: 0.25 | E11: 0.25 | F11: 0.25 | G11: 0.25 | H11: 0.25
B13: Balance Sheet & Cash Flow Assumptions
B14: Capital Expenditure ($ mm) | C14: 38 | D14: 40 | E14: 43 | F14: =E14+(((D14-C14)+(E14-D14))/2) -> 45.5 | G14: =F14+(((E14-D14)+(F14-E14))/2) -> 48.25 | H14: =G14+(((F14-E14)+(G14-F14))/2) -> 50.875
B15: Debt Repayment ($ mm) | C15: 0 | D15: 10 | E15: 10 | F15: 10 | G15: 10 | H15: 10
B17: DCF Assumptions
B18: WACC | C18: 0.1
B19: Terminal Growth Rate | C19: 0.035
B20: Shares Outstanding (mm) | C20: 100
B21: Net Debt (FY2024, $ mm) | C21: =('Balance Sheet'!E12 - 'Balance Sheet'!E5) -> -41.13616
B23: Note: Blue cells are hardcoded inputs. Projection years are 2025–2027. Historical data (2022–2024) is provided for reference.

Sheet Balance Sheet
B1: NEXFORGE MANUFACTURING — BALANCE SHEET ($ mm)
C3: 2022 | D3: 2023 | E3: 2024 | F3: 2025 | G3: 2026 | H3: 2027
B4: ASSETS
B5: Cash & Equivalents | C5: 45 | D5: =C5+'Cash Flow'!D15 -> 87.1096 | E5: =D5+'Cash Flow'!E15 -> 141.13616 | F5: =E5+'Cash Flow'!F15 -> 205.3612 | G5: =F5+'Cash Flow'!G15 -> 280.65664 | H5: =G5+'Cash Flow'!H15 -> 368.43594
B6: Accounts Receivable | C6: =12.5% *'Income Statement'!C4 -> 60 | D6: =12.5% *'Income Statement'!D4 -> 66 | E6: =12.5% *'Income Statement'!E4 -> 72.6 | F6: =12.5% *'Income Statement'!F4 -> 79.86 | G6: =12.5% *'Income Statement'!G4 -> 87.846 | H6: =12.5% *'Income Statement'!H4 -> 96.6306
B7: Inventory | C7: =25% *(-('Income Statement'!C5)) -> 72 | D7: =25% *(-('Income Statement'!D5)) -> 79.2 | E7: =25% *(-('Income Statement'!E5)) -> 87.12 | F7: =25% *(-('Income Statement'!F5)) -> 95.832 | G7: =25% *(-('Income Statement'!G5)) -> 105.4152 | H7: =25% *(-('Income Statement'!H5)) -> 115.95672
B8: PP&E, Net | C8: 240 | D8: =(C8 +Assumptions!D14)-Assumptions!D9 -> 250 | E8: =(D8 +Assumptions!E14)-Assumptions!E9 -> 260 | F8: =(E8 +Assumptions!F14)-Assumptions!F9 -> 270 | G8: =(F8 +Assumptions!G14)-Assumptions!G9 -> 280 | H8: =(G8 +Assumptions!H14)-Assumptions!H9 -> 290
B9: Total Assets | C9: =SUM(C5:C8) -> 417 | D9: =SUM(D5:D8) -> 482.3096 | E9: =SUM(E5:E8) -> 560.85616 | F9: =SUM(F5:F8) -> 651.0532 | G9: =SUM(G5:G8) -> 753.91784 | H9: =SUM(H5:H8) -> 871.02326
B10: LIABILITIES & EQUITY
B11: Accounts Payable | C11: =16.7%*(-('Income Statement'!C5)) -> 48.096 | D11: =16.7%*(-('Income Statement'!D5)) -> 52.9056 | E11: =16.7%*(-('Income Statement'!E5)) -> 58.19616 | F11: =16.7%*(-('Income Statement'!F5)) -> 64.015776 | G11: =16.7%*(-('Income Statement'!G5)) -> 70.417354 | H11: =16.7%*(-('Income Statement'!H5)) -> 77.459089
B12: Long-Term Debt | C12: 120 | D12: 110 | E12: 100 | F12: =E12 +'Cash Flow'!F13 -> 90 | G12: =F12 +'Cash Flow'!G13 -> 80 | H12: =G12 +'Cash Flow'!H13 -> 70
B13: Total Equity | C13: 249 | D13: =C13+'Income Statement'!D14 -> 319.5 | E13: =D13+'Income Statement'!E14 -> 402.756 | F13: =E13+'Income Statement'!F14 -> 497.13342 | G13: =F13+'Income Statement'!G14 -> 603.59648 | H13: =G13+'Income Statement'!H14 -> 723.66017
B14: Total Liab. & Equity | C14: =SUM(C11:C13) -> 417.096 | D14: =SUM(D11:D13) -> 482.4056 | E14: =SUM(E11:E13) -> 560.95216 | F14: =SUM(F11:F13) -> 651.1492 | G14: =SUM(G11:G13) -> 754.01384 | H14: =SUM(H11:H13) -> 871.11926
B16: Total L&E - Total Assets | C16: =C14-C9 -> 0.096 | D16: =D14-D9 -> 0.096 | E16: =E14-E9 -> 0.096 | F16: =F14-F9 -> 0.096 | G16: =G14-G9 -> 0.096 | H16: =H14-H9 -> 0.096

Sheet Income Statement
B1: NEXFORGE MANUFACTURING — INCOME STATEMENT ($ mm)
C3: 2022 | D3: 2023 | E3: 2024 | F3: 2025 | G3: 2026 | H3: 2027
B4: Revenue | C4: 480 | D4: 528 | E4: 580.8 | F4: =(E4*(1+Assumptions!F6)) -> 638.88 | G4: =(F4*(1+Assumptions!G6)) -> 702.768 | H4: =(G4*(1+Assumptions!G6)) -> 773.0448
B5: Cost of Goods Sold | C5: -288 | D5: -316.8 | E5: -348.48 | F5: =-(F4*Assumptions!F7) -> -383.328 | G5: =-(G4*Assumptions!G7) -> -421.6608 | H5: =-(H4*Assumptions!H7) -> -463.82688
B6: Gross Profit | C6: 192 | D6: 211.2 | E6: 232.32 | F6: =F4 + F5 -> 255.552 | G6: =G4 + G5 -> 281.1072 | H6: =H4 + H5 -> 309.21792
B7: SG&A Expenses | C7: -72 | D7: -79.2 | E7: -81.312 | F7: =-F4 * Assumptions!F8 -> -88.16544 | G7: =-G4 * Assumptions!G8 -> -95.576448 | H7: =-H4 * Assumptions!H8 -> -103.588
B8: EBITDA | C8: 120 | D8: 132 | E8: 151.008 | F8: =F6+F7 -> 167.38656 | G8: =G6+G7 -> 185.53075 | H8: =H6+H7 -> 205.62992
B9: D&A | C9: -28 | D9: -30 | E9: -33 | F9: =E9+(((D9-C9)+(E9-D9))/2) -> -35.5 | G9: =F9+(((E9-D9)+(F9-E9))/2) -> -38.25 | H9: =G9+(((F9-E9)+(G9-F9))/2) -> -40.875
B10: EBIT | C10: 92 | D10: 102 | E10: 118.008 | F10: =F8-Assumptions!F9 -> 131.88656 | G10: =G8-Assumptions!G9 -> 147.28075 | H10: =H8-Assumptions!H9 -> 164.75492
B11: Interest Expense | C11: -8 | D11: -8 | E11: -7 | F11: -6.05 | G11: -5.33 | H11: -4.67
B12: EBT | C12: 84 | D12: 94 | E12: 111.008 | F12: =F10+F11 -> 125.83656 | G12: =G10+G11 -> 141.95075 | H12: =H10+H11 -> 160.08492
B13: Income Tax | C13: -21 | D13: -23.5 | E13: -27.752 | F13: =(-(F12*Assumptions!F11)) -> -31.45914 | G13: =(-(G12*Assumptions!G11)) -> -35.487688 | H13: =(-(H12*Assumptions!H11)) -> -40.021229
B14: Net Income | C14: 63 | D14: 70.5 | E14: 83.256 | F14: =F12+F13 -> 94.37742 | G14: =G12+G13 -> 106.46306 | H14: =H12+H13 -> 120.06369
B15: Key Metrics
B16: EBITDA Margin | C16: 0.25 | D16: 0.25 | E16: 0.26 | F16: =(F8/F4)*100 -> 26.2 | G16: =(G8/G4)*100 -> 26.4 | H16: =(H8/H4)*100 -> 26.6
B17: Net Income Margin | C17: 0.13125 | D17: 0.13352273 | E17: 0.14334711 | F17: =(F14/F4) -> 0.14772323 | G17: =(G14/G4) -> 0.15149105 | H17: =(H14/H4) -> 0.15531272

Sheet Cash Flow
B1: NEXFORGE MANUFACTURING — CASH FLOW STATEMENT ($ mm)
C3: 2022 | D3: 2023 | E3: 2024 | F3: 2025 | G3: 2026 | H3: 2027
B4: Operating Activities
B5: Net Income | C5: 63 | D5: 70.5 | E5: 83.256 | F5: ='Income Statement'!F14 -> 94.37742 | G5: ='Income Statement'!G14 -> 106.46306 | H5: ='Income Statement'!H14 -> 120.06369
B6: Add: D&A | C6: 28 | D6: 30 | E6: 33 | F6: =E6+(((D6-C6)+(E6-D6))/2) -> 35.5 | G6: =F6+(((E6-D6)+(F6-E6))/2) -> 38.25 | H6: =(G6+(((F6-E6)+(G6-F6))/2)) -> 40.875
B7: Change in Working Capital | C7: 0 | D7: =(('Balance Sheet'!C6+'Balance Sheet'!C7)-'Balance Sheet'!C11) - (('Balance Sheet'!D6+'Balance Sheet'!D7)-'Balance Sheet'!D11) -> -8.3904 | E7: =(('Balance Sheet'!D6+'Balance Sheet'!D7)-'Balance Sheet'!D11) - (('Balance Sheet'!E6+'Balance Sheet'!E7)-'Balance Sheet'!E11) -> -9.22944 | F7: =(('Balance Sheet'!E6+'Balance Sheet'!E7)-'Balance Sheet'!E11) - (('Balance Sheet'!F6+'Balance Sheet'!F7)-'Balance Sheet'!F11) -> -10.152384 | G7: =(('Balance Sheet'!F6+'Balance Sheet'!F7)-'Balance Sheet'!F11) - (('Balance Sheet'!G6+'Balance Sheet'!G7)-'Balance Sheet'!G11) -> -11.167622 | H7: =(('Balance Sheet'!G6+'Balance Sheet'!G7)-'Balance Sheet'!G11) - (('Balance Sheet'!H6+'Balance Sheet'!H7)-'Balance Sheet'!H11) -> -12.284385
B8: Cash from Operations | C8: 91 | D8: =(D5+D6+D7) -> 92.1096 | E8: =(E5+E6+E7) -> 107.02656 | F8: =(F5+F6+F7) -> 119.72504 | G8: =(G5+G6+G7) -> 133.54544 | H8: =(H5+H6+H7) -> 148.6543
B9: Investing Activities
B10: Capital Expenditures | C10: -38 | D10: -40 | E10: -43 | F10: =(-Assumptions!F14) -> -45.5 | G10: =(-Assumptions!G14) -> -48.25 | H10: =(-Assumptions!H14) -> -50.875
B11: Cash from Investing | C11: -38 | D11: -40 | E11: -43 | F11: =(-Assumptions!F14) -> -45.5 | G11: =(-Assumptions!G14) -> -48.25 | H11: =(-Assumptions!H14) -> -50.875
B12: Financing Activities
B13: Debt Repayment | C13: 0 | D13: -10 | E13: -10 | F13: -10 | G13: -10 | H13: -10
B14: Cash from Financing | C14: 0 | D14: -10 | E14: -10 | F14: -10 | G14: -10 | H14: -10
B15: Net Change in Cash | C15: =C8+C11+C14 -> 53 | D15: =D8+D11+D14 -> 42.1096 | E15: =E8+E11+E14 -> 54.02656 | F15: =F8+F11+F14 -> 64.225036 | G15: =G8+G11+G14 -> 75.295442 | H15: =H8+H11+H14 -> 87.779303

Sheet DCF Valuation
B1: NEXFORGE MANUFACTURING — DCF VALUATION ($ mm)
B2: Step 1: Free Cash Flow Build
C3: 2025 | D3: 2026 | E3: 2027 | F3: 2028
B4: EBIT | C4: ='Income Statement'!F10 -> 131.88656 | D4: ='Income Statement'!G10 -> 147.28075 | E4: ='Income Statement'!H10 -> 164.75492
B5: Less: Taxes on EBIT | C5: =Assumptions!F11*'DCF Valuation'!C4 -> 32.97164 | D5: =Assumptions!G11*'DCF Valuation'!D4 -> 36.820188 | E5: =Assumptions!H11*'DCF Valuation'!E4 -> 41.188729
B6: NOPAT | C6: =C4-C5 -> 98.91492 | D6: =D4-D5 -> 110.46056 | E6: =E4-E5 -> 123.56619
B7: Add: D&A | C7: =Assumptions!F9 -> 35.5 | D7: =Assumptions!G9 -> 38.25 | E7: =Assumptions!H9 -> 40.875
B8: Less: CapEx | C8: =Assumptions!F14 -> 45.5 | D8: =Assumptions!G14 -> 48.25 | E8: =Assumptions!H14 -> 50.875
B9: Change in Working Capital | C9: =-('Cash Flow'!F7) -> 10.152384 | D9: =-('Cash Flow'!G7) -> 11.167622 | E9: =-('Cash Flow'!H7) -> 12.284385
B10: Free Cash Flow (FCF) | C10: =(C6+C7)-(C8+C9) -> 78.762536 | D10: =(D6+D7)-(D8+D9) -> 89.292942 | E10: =(E6+E7)-(E8+E9) -> 101.2818 | F10: =E10*(1+Assumptions!C19) -> 104.82667
B11: Step 2: Discount Cash Flows
C12: 2025 | D12: 2026 | E12: 2027 | F12: 2028
B13: Discount Period | C13: 1 | D13: 2 | E13: 3 | F13: 4
B14: Discount Factor | C14: =1/(1+Assumptions!C18)^'DCF Valuation'!C13 -> 0.90909091 | D14: =1/(1+Assumptions!C18)^'DCF Valuation'!D13 -> 0.82644628 | E14: =1/(1+Assumptions!C18)^'DCF Valuation'!E13 -> 0.7513148 | F14: =1/(1+Assumptions!C18)^'DCF Valuation'!F13 -> 0.68301346
B15: PV of FCF | C15: =C10*C14 -> 71.602305 | D15: =D10*D14 -> 73.79582 | E15: =E10*E14 -> 76.094518 | F15: =F10*F14 -> 71.598023
B17: Step 3: Terminal Value & Valuation Summary
B18: Sum of PV of FCFs ($ mm) | C18: =SUM(C15:E15) -> 221.49264
B19: Terminal Value ($ mm) | C19: =F10/(Assumptions!C18-Assumptions!C19) -> 1612.7179
B20: PV of Terminal Value ($ mm) | C20: =C19/(1+Assumptions!C18)^'DCF Valuation'!E13 -> 1211.6589
B21: Enterprise Value ($ mm) | C21: =SUM(C15:E15)+C20 -> 1433.1515
B22: Less: Net Debt ($ mm) | C22: =(Assumptions!C21) -> -41.13616
B23: Equity Value ($ mm) | C23: =C21-C22 -> 1474.2877
B24: Shares Outstanding (mm) | C24: =Assumptions!C20 -> 100
B25: Implied Share Price ($) | C25: =C23/C24 -> 14.742877
